sensetdp/__init__.py
sensetdp/api.py
sensetdp/auth.py
sensetdp/binder.py
sensetdp/error.py
sensetdp/models.py
sensetdp/parsers.py
sensetdp/utils.py
sensetdp/vocabulary.py
sensetdp-2.0.4.dist-info/DESCRIPTION.rst
sensetdp-2.0.4.dist-info/METADATA
sensetdp-2.0.4.dist-info/RECORD
sensetdp-2.0.4.dist-info/WHEEL
sensetdp-2.0.4.dist-info/metadata.json
sensetdp-2.0.4.dist-info/top_level.txt
sensetdp-2.0.4.dist-info/zip-safe
