Metadata-Version: 2.0
Name: sensetdp
Version: 2.0.4
Summary: Sense-T Data Portal v2 client
Home-page: https://github.com/ionata/senset-data-portal
Author: Ionata Digital
Author-email: developers@ionata.com.au
License: MIT
Keywords: sense-t api client library
Platform: UNKNOWN
Classifier: Development Status :: 4 - Beta
Classifier: Topic :: Software Development :: Libraries
Classifier: License :: OSI Approved :: MIT License
Classifier: Operating System :: OS Independent
Classifier: Programming Language :: Python
Classifier: Programming Language :: Python :: 2
Classifier: Programming Language :: Python :: 2.7
Classifier: Programming Language :: Python :: 3
Classifier: Programming Language :: Python :: 3.4
Requires-Dist: requests[security] (==2.9.1)
Requires-Dist: six (>=1.7.3)
Requires-Dist: enum34 (==1.1.2)
